wsc_grempy_transport/__init__.py
wsc_grempy_transport/transport.py
wsc_grempy_transport-0.1.0.dist-info/LICENSE
wsc_grempy_transport-0.1.0.dist-info/METADATA
wsc_grempy_transport-0.1.0.dist-info/WHEEL
wsc_grempy_transport-0.1.0.dist-info/top_level.txt
wsc_grempy_transport-0.1.0.dist-info/RECORD
