Metadata-Version: 2.1
Name: wsc-grempy-transport
Version: 0.1.0
Summary: Supports gremlinpython without asyncio
Home-page: https://github.com/skieffer/wsc-grempy-transport
License: Apache 2.0
Platform: UNKNOWN
Classifier: License :: OSI Approved :: Apache Software License
Classifier: Operating System :: OS Independent
Classifier: Programming Language :: Python :: 3
License-File: LICENSE
Requires-Dist: gremlinpython (>=3.5.0)
Requires-Dist: websocket-client (>=1.3.0)
